setup.py
lightning_crm/__init__.py
lightning_crm/admin.py
lightning_crm/apps.py
lightning_crm/models.py
lightning_crm/tests.py
lightning_crm/views.py
lightning_crm.egg-info/PKG-INFO
lightning_crm.egg-info/SOURCES.txt
lightning_crm.egg-info/dependency_links.txt
lightning_crm.egg-info/not-zip-safe
lightning_crm.egg-info/requires.txt
lightning_crm.egg-info/top_level.txt
lightning_crm/migrations/0001_initial.py
lightning_crm/migrations/__init__.py