Metadata-Version: 1.1
Name: lightning-crm
Version: 0.1.0
Summary: CRM for lightning
Home-page: https://github.com/git-men/lightning-crm
Author: gitmen.com
Author-email: jeff@gitmen.com
License: MIT
Platform: UNKNOWN
Classifier: Intended Audience :: Developers
Classifier: Programming Language :: Python
Classifier: Programming Language :: Python :: 3
Classifier: Programming Language :: Python :: 3.6
Classifier: Programming Language :: Python :: 3.7
Classifier: Programming Language :: Python :: 3 :: Only
Classifier: Topic :: Software Development :: Libraries :: Python Modules
